fastapi_myhelper/__init__.py
fastapi_myhelper/pydantic/__init__.py
fastapi_myhelper/pydantic/meta.py
fastapi_myhelper/sqlalchemy/__init__.py
fastapi_myhelper/sqlalchemy/pagination.py
fastapi_myhelper/sqlalchemy/utils.py
fastapi_myhelper/sqlmodel/__init__.py
fastapi_myhelper/sqlmodel/meta.py
fastapi_myhelper/sqlmodel/utils.py
fastapi_myhelper/strawberry/__init__.py
fastapi_myhelper/strawberry/decorators.py
fastapi_myhelper/strawberry/exceptions.py
fastapi_myhelper/strawberry/extentions/__init__.py
fastapi_myhelper/strawberry/extentions/errors.py
fastapi_myhelper/strawberry/relationship.py
fastapi_myhelper/strawberry/schemas/__init__.py
fastapi_myhelper/strawberry/schemas/meta.py
fastapi_myhelper/strawberry/schemas/pagination.py
fastapi_myhelper/strawberry/schemas/schema.py
fastapi_myhelper/strawberry/schemas/type.py
fastapi_myhelper/strawberry/sqlalchemy/__init__.py
fastapi_myhelper/strawberry/sqlalchemy/query.py
fastapi_myhelper/strawberry/sqlalchemy/utils.py
fastapi_myhelper/strawberry/sqlmodel/__init__.py
fastapi_myhelper/strawberry/sqlmodel/utils.py
fastapi_myhelper/strawberry/utils.py
fastapi_myhelper/tests/__init__.py
fastapi_myhelper/tests/strawberry/__init__.py
fastapi_myhelper/tests/strawberry/test_pydantic.py
fastapi_myhelper/tests/strawberry/test_schema.py
fastapi_myhelper/tests/strawberry/test_sqlalchemy.py
fastapi_myhelper/tests/strawberry/test_sqlmodel.py
fastapi_myhelper/tests/strawberry/test_validator.py
fastapi_myhelper-0.1.7.dist-info/WHEEL
fastapi_myhelper-0.1.7.dist-info/METADATA
fastapi_myhelper-0.1.7.dist-info/RECORD
