Metadata-Version: 2.1
Name: fastapi-myhelper
Version: 0.1.7
Summary: 
Author: MihaTeam1
Author-email: sarsern2004@gmail.com
Requires-Python: >=3.9,<4.0
Classifier: Programming Language :: Python :: 3
Classifier: Programming Language :: Python :: 3.9
Classifier: Programming Language :: Python :: 3.10
Classifier: Programming Language :: Python :: 3.11
Provides-Extra: all
Provides-Extra: pydantic
Provides-Extra: sqlalchemy
Provides-Extra: sqlmodel
Provides-Extra: strawberry
Requires-Dist: pydantic (>=1.10.4,<2.0.0) ; extra == "sqlmodel" or extra == "pydantic"
Requires-Dist: sqlalchemy (>=1.4.17,<=1.4.41) ; extra == "sqlmodel" or extra == "sqlalchemy"
Requires-Dist: sqlmodel (>=0.0.8,<0.0.9) ; extra == "all" or extra == "sqlmodel"
Requires-Dist: strawberry-graphql (>=0.155.3,<0.156.0) ; extra == "all" or extra == "strawberry"
